CHANGELOG.md
MANIFEST.in
README.rst
setup.cfg
setup.py
rattail_quickbooks/__init__.py
rattail_quickbooks/_version.py
rattail_quickbooks.egg-info/PKG-INFO
rattail_quickbooks.egg-info/SOURCES.txt
rattail_quickbooks.egg-info/dependency_links.txt
rattail_quickbooks.egg-info/requires.txt
rattail_quickbooks.egg-info/top_level.txt
rattail_quickbooks/db/__init__.py
rattail_quickbooks/db/alembic/versions/6a6791ac0961_add_invoice_shipping_supplies.py
rattail_quickbooks/db/alembic/versions/72134a69c576_initial_integration_tables.py
rattail_quickbooks/db/alembic/versions/73ec806dc87b_add_quickbooksvendorbankaccount.py
rattail_quickbooks/db/model/__init__.py
rattail_quickbooks/db/model/invoices.py
rattail_quickbooks/db/model/org.py
rattail_quickbooks/db/model/stores.py
rattail_quickbooks/db/model/vendors.py
rattail_quickbooks/importing/__init__.py
rattail_quickbooks/importing/model.py
rattail_quickbooks/importing/versions.py